indicis/__init__.py
indicis/cdi.py
indicis/difuturo.py
indicis/ipca.py
indicis-0.0.2.dist-info/LICENSE
indicis-0.0.2.dist-info/METADATA
indicis-0.0.2.dist-info/WHEEL
indicis-0.0.2.dist-info/top_level.txt
indicis-0.0.2.dist-info/RECORD
