Metadata-Version: 2.1
Name: indicis
Version: 0.0.2
Summary: Bibliotera de parser para indices do mercado brasileiro
Home-page: https://github.com/jurusbr/indicis
Author: Gustavo Barros
Author-email: gustavo.barros@jurus.com.br
License: UNKNOWN
Platform: UNKNOWN
Classifier: Programming Language :: Python :: 3
Classifier: License :: OSI Approved :: MIT License
Classifier: Operating System :: OS Independent
Requires-Python: >=3.6
